rocks/__init__.py
rocks/bft.py
rocks/cache.py
rocks/cli.py
rocks/config.py
rocks/core.py
rocks/datacloud.py
rocks/index.py
rocks/logging.py
rocks/metadata.py
rocks/plots.py
rocks/resolve.py
rocks/ssodnet.py
space_rocks-1.9.15.dist-info/LICENSE
space_rocks-1.9.15.dist-info/METADATA
space_rocks-1.9.15.dist-info/WHEEL
space_rocks-1.9.15.dist-info/entry_points.txt
space_rocks-1.9.15.dist-info/RECORD
