Metadata-Version: 2.3
Name: space-rocks
Version: 1.9.15
Summary: Python client for SsODNet data access.
License: MIT
Author: Max Mahlke
Author-email: max.mahlke@oca.eu
Requires-Python: >=3.8
Classifier: License :: OSI Approved :: MIT License
Classifier: Programming Language :: Python :: 3
Classifier: Programming Language :: Python :: 3.8
Classifier: Programming Language :: Python :: 3.9
Classifier: Programming Language :: Python :: 3.10
Classifier: Programming Language :: Python :: 3.11
Classifier: Programming Language :: Python :: 3.12
Classifier: Programming Language :: Python :: 3.13
Provides-Extra: docs
Requires-Dist: Levenshtein (>=0.16.0)
Requires-Dist: aiodns (>=3.1.0)
Requires-Dist: aiohttp (>=3.9.2)
Requires-Dist: click (>=8.1.2)
Requires-Dist: faust-cchardet (>=2.1.7)
Requires-Dist: matplotlib (>=3.4.3)
Requires-Dist: nest-asyncio (>=1.5.1)
Requires-Dist: numpy (>=1.21) ; python_version >= "3.7" and python_version < "3.11"
Requires-Dist: numpy (>=1.24) ; python_version >= "3.11" and python_version < "4.0"
Requires-Dist: pandas (>=1.3.5)
Requires-Dist: platformdirs (>=2.6.2)
Requires-Dist: pydantic (<=2.10)
Requires-Dist: rapidfuzz (>=3)
Requires-Dist: requests (>=2.26.0)
Requires-Dist: rich (>=12.2.0)
Project-URL: Documentation, https://rocks.readthedocs.io/en/latest/
Project-URL: Homepage, https://rocks.readthedocs.io/en/latest/
Project-URL: Repository, https://github.com/maxmahlke/rocks.git
